__init__.py
aghelper/types/__init__.py
aghelper/types/simple_namespace.py
aghelper/utils/__init__.py
aghelper/utils/safe_executor.py
ag_helper-0.0.4.dist-info/LICENSE
ag_helper-0.0.4.dist-info/METADATA
ag_helper-0.0.4.dist-info/WHEEL
ag_helper-0.0.4.dist-info/top_level.txt
ag_helper-0.0.4.dist-info/RECORD
