Metadata-Version: 2.1
Name: ag-helper
Version: 0.0.4
Summary: Personal helpers package
Author-email: Alexandr Kozlov <alex.gadfly@gmail.com>
Project-URL: Homepage, https://gitlab.enet.vn.ua/alexandrgadfly/aghelpers
Classifier: Programming Language :: Python :: 3
Classifier: License :: OSI Approved :: MIT License
Classifier: Operating System :: OS Independent
Requires-Python: >=3.7
License-File: LICENSE
